kef/__init__.py
kef/cli.py
kef/config.py
kef/py.typed
kef-0.1.2.dist-info/WHEEL
kef-0.1.2.dist-info/entry_points.txt
kef-0.1.2.dist-info/METADATA
kef-0.1.2.dist-info/RECORD
