Metadata-Version: 2.3
Name: kef
Version: 0.1.2
Summary: Configuration management package for Kaggle projects using OmegaConf
Keywords: kaggle,configuration,omegaconf,ml,data science
Author: Emmanuel Roux
Author-email: Emmanuel Roux <15956441+fesaille@users.noreply.github.com>
License: MIT
Classifier: Development Status :: 4 - Beta
Classifier: Intended Audience :: Developers
Classifier: Intended Audience :: Science/Research
Classifier: License :: OSI Approved :: MIT License
Classifier: Programming Language :: Python :: 3.12
Classifier: Topic :: Scientific/Engineering
Classifier: Topic :: Software Development :: Libraries :: Python Modules
Requires-Dist: click>=8.3.1
Requires-Dist: omegaconf>=2.3.0
Requires-Dist: rich>=14.2.0
Requires-Python: >=3.12, <3.14
Project-URL: Homepage, https://github.com/e-roux/sbx-kaggle
Project-URL: Issues, https://github.com/e-roux/sbx-kaggle/issues
Project-URL: Repository, https://github.com/e-roux/sbx-kaggle.git
